[
  {
    "id": 2380920,
    "name": "Tem trùm Kawasaki Ninja 400 Hồng Đen Dreamer cực chất",
    "code": "",
    "img": "http://upload2.webbnc.vn/uploadv2/web/97/9724/product/2022/07/24/09/24/1658648539_img_1655543531288_1655545464223.jpg",
    "subImg": [
      "http://upload2.webbnc.vn/uploadv2/web/97/9724/product/2022/07/24/09/24/1658648531_img_1655543531282_1655545457815.jpg",
      "http://upload2.webbnc.vn/uploadv2/web/97/9724/product/2022/07/24/09/24/1658648533_img_1655543531284_1655545460357.jpg",
      "http://upload2.webbnc.vn/uploadv2/web/97/9724/product/2022/07/24/09/24/1658648536_img_1655543531286_1655545462322.jpg",
      "http://upload2.webbnc.vn/uploadv2/web/97/9724/product/2022/07/24/09/24/1658648539_img_1655543531288_1655545464223.jpg"
    ],
    "seo": "tem-trum-kawasaki-ninja-400-hong-den-dreamer-cuc-chat",
    "shortDescription": "FREESHIP tem toàn quốc & thiết kế theo yêu cầu Có dịch vụ ship tem xe ra nước ngoài Đặt lịch & tư vấn decal tem xe liên hệ Zalo 0904560191. Khách hàng có thể tùy chỉnh thiết kế tem bằng cách thêm têm,\nsố hay logo... thậm chí đổi màu sắc và chất liệu theo ý thích của bạn. Vui lòng liên hệ để được tư vấn tốt nhất!\nBảo hành 12 tháng về tem khi dán trực tiếp tại cửa hàng.\n ",
    "longDescription": "FREESHIP tem toàn quốc & thiết kế theo yêu cầu Có dịch vụ ship tem xe ra nước ngoài Đặt lịch & tư vấn decal tem xe liên hệ Zalo 0904560191. Khách hàng có thể tùy chỉnh thiết kế tem bằng cách thêm têm,\nsố hay logo... thậm chí đổi màu sắc và chất liệu theo ý thích của bạn. Vui lòng liên hệ để được tư vấn tốt nhất!\nBảo hành 12 tháng về tem khi dán trực tiếp tại cửa hàng.\n\nVì sao lựa chọn tem xe của Q-Decal? \n> Chất liệu cao cấp nhập khẩu 100% loại 3 lớp cực bền\n> Co giãn 4 chiều thoải mái và giấy rất dày dặn\n> Tùy chọn chất liệu thường, nhôm hoặc nhôm xước \n> Tem được cán 1 lớp bảo vệ nhám hoặc mờ tùy theo yêu cầu ",
    "price": "0",
    "categoryName": "",
    "categoryPath": ""
  },
  {
    "id": 2380918,
    "name": "Tem trùm Winner V3 phong cách Porsche Đỏ Trắng sang trọng decal 3 lớp cao cấp",
    "code": "",
    "img": "http://upload2.webbnc.vn/uploadv2/web/97/9724/product/2022/07/24/09/18/1658648203_img_1657336848616_1657349073804.jpg",
    "subImg": [
      "http://upload2.webbnc.vn/uploadv2/web/97/9724/product/2022/07/24/09/18/1658648203_img_1657336848616_1657349073804.jpg"
    ],
    "seo": "tem-trum-winner-v3-phong-cach-porsche-do-trang-sang-trong-decal-3-lop-cao-cap",
    "shortDescription": "FREESHIP tem toàn quốc & thiết kế theo yêu cầu Có dịch vụ ship tem xe ra nước ngoài Đặt lịch & tư vấn decal tem xe liên hệ Zalo 0904560191. Khách hàng có thể tùy chỉnh thiết kế tem bằng cách thêm têm,\nsố hay logo... thậm chí đổi màu sắc và chất liệu theo ý thích của bạn. Vui lòng liên hệ để được tư vấn tốt nhất!\nBảo hành 12 tháng về tem khi dán trực tiếp tại cửa hàng.\n ",
    "longDescription": "FREESHIP tem toàn quốc & thiết kế theo yêu cầu Có dịch vụ ship tem xe ra nước ngoài Đặt lịch & tư vấn decal tem xe liên hệ Zalo 0904560191. Khách hàng có thể tùy chỉnh thiết kế tem bằng cách thêm têm,\nsố hay logo... thậm chí đổi màu sắc và chất liệu theo ý thích của bạn. Vui lòng liên hệ để được tư vấn tốt nhất!\nBảo hành 12 tháng về tem khi dán trực tiếp tại cửa hàng.\n\nVì sao lựa chọn tem xe của Q-Decal? \n> Chất liệu cao cấp nhập khẩu 100% loại 3 lớp cực bền\n> Co giãn 4 chiều thoải mái và giấy rất dày dặn\n> Tùy chọn chất liệu thường, nhôm hoặc nhôm xước \n> Tem được cán 1 lớp bảo vệ nhám hoặc mờ tùy theo yêu cầu ",
    "price": "380000",
    "categoryName": "",
    "categoryPath": ""
  },
  {
    "id": 2380916,
    "name": "Tem trùm Winner V3 Bạc Xám Redbull Candy Cao cấp",
    "code": "",
    "img": "http://upload2.webbnc.vn/uploadv2/web/97/9724/product/2022/07/24/09/16/1658648058_img_1657336728248_1657349071901.jpg",
    "subImg": [
      "http://upload2.webbnc.vn/uploadv2/web/97/9724/product/2022/07/24/09/16/1658648058_img_1657336728248_1657349071901.jpg"
    ],
    "seo": "tem-trum-winner-v3-bac-xam-redbull-candy-cao-cap",
    "shortDescription": "FREESHIP tem toàn quốc & thiết kế theo yêu cầu Có dịch vụ ship tem xe ra nước ngoài Đặt lịch & tư vấn decal tem xe liên hệ Zalo 0904560191. Khách hàng có thể tùy chỉnh thiết kế tem bằng cách thêm têm,\nsố hay logo... thậm chí đổi màu sắc và chất liệu theo ý thích của bạn. Vui lòng liên hệ để được tư vấn tốt nhất!\nBảo hành 12 tháng về tem khi dán trực tiếp tại cửa hàng.",
    "longDescription": "FREESHIP tem toàn quốc & thiết kế theo yêu cầu Có dịch vụ ship tem xe ra nước ngoài Đặt lịch & tư vấn decal tem xe liên hệ Zalo 0904560191. Khách hàng có thể tùy chỉnh thiết kế tem bằng cách thêm têm,\nsố hay logo... thậm chí đổi màu sắc và chất liệu theo ý thích của bạn. Vui lòng liên hệ để được tư vấn tốt nhất!\nBảo hành 12 tháng về tem khi dán trực tiếp tại cửa hàng.\n\nVì sao lựa chọn tem xe của Q-Decal? \n> Chất liệu cao cấp nhập khẩu 100% loại 3 lớp cực bền\n> Co giãn 4 chiều thoải mái và giấy rất dày dặn\n> Tùy chọn chất liệu thường, nhôm hoặc nhôm xước \n> Tem được cán 1 lớp bảo vệ nhám hoặc mờ tùy theo yêu cầu ",
    "price": "580000",
    "categoryName": "",
    "categoryPath": ""
  },
  {
    "id": 2380914,
    "name": "Tem trùm Winner X V3 MX King Đen Xanh lá decal 3 lớp Cao Cấp",
    "code": "",
    "img": "http://upload2.webbnc.vn/uploadv2/web/97/9724/product/2022/07/24/09/15/1658648013_img_1656758445133_1656758645409.jpg",
    "subImg": [
      "http://upload2.webbnc.vn/uploadv2/web/97/9724/product/2022/07/24/09/15/1658648013_img_1656758445133_1656758645409.jpg"
    ],
    "seo": "tem-trum-winner-x-v3-mx-king-den-xanh-la-decal-3-lop-cao-c",
    "shortDescription": "FREESHIP tem toàn quốc & thiết kế theo yêu cầu Có dịch vụ ship tem xe ra nước ngoài Đặt lịch & tư vấn decal tem xe liên hệ Zalo 0904560191. Khách hàng có thể tùy chỉnh thiết kế tem bằng cách thêm têm,\nsố hay logo... thậm chí đổi màu sắc và chất liệu theo ý thích của bạn. Vui lòng liên hệ để được tư vấn tốt nhất!\nBảo hành 12 tháng về tem khi dán trực tiếp tại cửa hàng.",
    "longDescription": "FREESHIP tem toàn quốc & thiết kế theo yêu cầu Có dịch vụ ship tem xe ra nước ngoài Đặt lịch & tư vấn decal tem xe liên hệ Zalo 0904560191. Khách hàng có thể tùy chỉnh thiết kế tem bằng cách thêm têm,\nsố hay logo... thậm chí đổi màu sắc và chất liệu theo ý thích của bạn. Vui lòng liên hệ để được tư vấn tốt nhất!\nBảo hành 12 tháng về tem khi dán trực tiếp tại cửa hàng.\n\nVì sao lựa chọn tem xe của Q-Decal? \n> Chất liệu cao cấp nhập khẩu 100% loại 3 lớp cực bền\n> Co giãn 4 chiều thoải mái và giấy rất dày dặn\n> Tùy chọn chất liệu thường, nhôm hoặc nhôm xước \n> Tem được cán 1 lớp bảo vệ nhám hoặc mờ tùy theo yêu cầu ",
    "price": "380000",
    "categoryName": "",
    "categoryPath": ""
  },
  {
    "id": 2380912,
    "name": "Tem trùm Winner V3 tổ ong huyền thoại Trắng Đỏ Đen decal 3 lớp cao cấp",
    "code": "",
    "img": "http://upload2.webbnc.vn/uploadv2/web/97/9724/product/2022/07/24/09/14/1658647970_img_1656758412157_1656758645150.jpg",
    "subImg": [
      "http://upload2.webbnc.vn/uploadv2/web/97/9724/product/2022/07/24/09/14/1658647970_img_1656758412157_1656758645150.jpg"
    ],
    "seo": "tem-trum-winner-v3-to-ong-huyen-thoai-trang-do-den-decal-3-lop-cao-ca",
    "shortDescription": "FREESHIP tem toàn quốc & thiết kế theo yêu cầu Có dịch vụ ship tem xe ra nước ngoài Đặt lịch & tư vấn decal tem xe liên hệ Zalo 0904560191. Khách hàng có thể tùy chỉnh thiết kế tem bằng cách thêm têm,\nsố hay logo... thậm chí đổi màu sắc và chất liệu theo ý thích của bạn. Vui lòng liên hệ để được tư vấn tốt nhất!\nBảo hành 12 tháng về tem khi dán trực tiếp tại cửa hàng.\n ",
    "longDescription": "FREESHIP tem toàn quốc & thiết kế theo yêu cầu Có dịch vụ ship tem xe ra nước ngoài Đặt lịch & tư vấn decal tem xe liên hệ Zalo 0904560191. Khách hàng có thể tùy chỉnh thiết kế tem bằng cách thêm têm,\nsố hay logo... thậm chí đổi màu sắc và chất liệu theo ý thích của bạn. Vui lòng liên hệ để được tư vấn tốt nhất!\nBảo hành 12 tháng về tem khi dán trực tiếp tại cửa hàng.\n\nVì sao lựa chọn tem xe của Q-Decal? \n> Chất liệu cao cấp nhập khẩu 100% loại 3 lớp cực bền\n> Co giãn 4 chiều thoải mái và giấy rất dày dặn\n> Tùy chọn chất liệu thường, nhôm hoặc nhôm xước \n> Tem được cán 1 lớp bảo vệ nhám hoặc mờ tùy theo yêu cầu ",
    "price": "380000",
    "categoryName": "",
    "categoryPath": ""
  },
  {
    "id": 2380910,
    "name": "Tem trùm Winner X V3 Hắc Bạch Vô Thường Đen Trắng decal 3 lớp cao cấp",
    "code": "",
    "img": "http://upload2.webbnc.vn/uploadv2/web/97/9724/product/2022/07/24/09/13/1658647903_img_1656758385994_1656758644736.jpg",
    "subImg": [
      "http://upload2.webbnc.vn/uploadv2/web/97/9724/product/2022/07/24/09/13/1658647903_img_1656758385994_1656758644736.jpg"
    ],
    "seo": "tem-trum-winner-x-v3-hac-bach-vo-thuong-den-trang-decal-3-lop-cao-ca",
    "shortDescription": "FREESHIP tem toàn quốc & thiết kế theo yêu cầu Có dịch vụ ship tem xe ra nước ngoài Đặt lịch & tư vấn decal tem xe liên hệ Zalo 0904560191. Khách hàng có thể tùy chỉnh thiết kế tem bằng cách thêm têm,\nsố hay logo... thậm chí đổi màu sắc và chất liệu theo ý thích của bạn. Vui lòng liên hệ để được tư vấn tốt nhất!\nBảo hành 12 tháng về tem khi dán trực tiếp tại cửa hàng.\n ",
    "longDescription": "FREESHIP tem toàn quốc & thiết kế theo yêu cầu Có dịch vụ ship tem xe ra nước ngoài Đặt lịch & tư vấn decal tem xe liên hệ Zalo 0904560191. Khách hàng có thể tùy chỉnh thiết kế tem bằng cách thêm têm,\nsố hay logo... thậm chí đổi màu sắc và chất liệu theo ý thích của bạn. Vui lòng liên hệ để được tư vấn tốt nhất!\nBảo hành 12 tháng về tem khi dán trực tiếp tại cửa hàng.\n\nVì sao lựa chọn tem xe của Q-Decal? \n> Chất liệu cao cấp nhập khẩu 100% loại 3 lớp cực bền\n> Co giãn 4 chiều thoải mái và giấy rất dày dặn\n> Tùy chọn chất liệu thường, nhôm hoặc nhôm xước \n> Tem được cán 1 lớp bảo vệ nhám hoặc mờ tùy theo yêu cầu ",
    "price": "380000",
    "categoryName": "",
    "categoryPath": ""
  },
  {
    "id": 2380908,
    "name": "Tem trùm Winner V3 Hello Kitty Trắng Hồng Xinh ơi là Xinh",
    "code": "",
    "img": "http://upload2.webbnc.vn/uploadv2/web/97/9724/product/2022/07/24/09/12/1658647836_img_1656758315330_1656758644402.jpg",
    "subImg": [
      "http://upload2.webbnc.vn/uploadv2/web/97/9724/product/2022/07/24/09/12/1658647836_img_1656758315330_1656758644402.jpg"
    ],
    "seo": "tem-trum-winner-v3-hello-kitty-trang-hong-xinh-oi-la-xinh",
    "shortDescription": "FREESHIP tem toàn quốc & thiết kế theo yêu cầu Có dịch vụ ship tem xe ra nước ngoài Đặt lịch & tư vấn decal tem xe liên hệ Zalo 0904560191. Khách hàng có thể tùy chỉnh thiết kế tem bằng cách thêm têm,\nsố hay logo... thậm chí đổi màu sắc và chất liệu theo ý thích của bạn. Vui lòng liên hệ để được tư vấn tốt nhất!\nBảo hành 12 tháng về tem khi dán trực tiếp tại cửa hàng.\n ",
    "longDescription": "FREESHIP tem toàn quốc & thiết kế theo yêu cầu Có dịch vụ ship tem xe ra nước ngoài Đặt lịch & tư vấn decal tem xe liên hệ Zalo 0904560191. Khách hàng có thể tùy chỉnh thiết kế tem bằng cách thêm têm,\nsố hay logo... thậm chí đổi màu sắc và chất liệu theo ý thích của bạn. Vui lòng liên hệ để được tư vấn tốt nhất!\nBảo hành 12 tháng về tem khi dán trực tiếp tại cửa hàng.\n\nVì sao lựa chọn tem xe của Q-Decal? \n> Chất liệu cao cấp nhập khẩu 100% loại 3 lớp cực bền\n> Co giãn 4 chiều thoải mái và giấy rất dày dặn\n> Tùy chọn chất liệu thường, nhôm hoặc nhôm xước \n> Tem được cán 1 lớp bảo vệ nhám hoặc mờ tùy theo yêu cầu ",
    "price": "380000",
    "categoryName": "",
    "categoryPath": ""
  },
  {
    "id": 2380906,
    "name": "Tem trùm WinnerX chia đôi cơn mơ Đỏ Đen decal candy mờ cao cấp",
    "code": "",
    "img": "http://upload2.webbnc.vn/uploadv2/web/97/9724/product/2022/07/24/08/57/1658646921_img_1638098804431_1638098843348.jpg",
    "subImg": [
      "http://upload2.webbnc.vn/uploadv2/web/97/9724/product/2022/07/24/08/57/1658646909_img_1638098804426_1638098830420.jpg",
      "http://upload2.webbnc.vn/uploadv2/web/97/9724/product/2022/07/24/08/57/1658646912_img_1638098804428_1638098830650.jpg",
      "http://upload2.webbnc.vn/uploadv2/web/97/9724/product/2022/07/24/08/57/1658646914_img_1638098804429_1638098830723.jpg",
      "http://upload2.webbnc.vn/uploadv2/web/97/9724/product/2022/07/24/08/57/1658646918_img_1638098804430_1638098839275.jpg",
      "http://upload2.webbnc.vn/uploadv2/web/97/9724/product/2022/07/24/08/57/1658646921_img_1638098804431_1638098843348.jpg"
    ],
    "seo": "tem-trum-winnerx-chia-doi-con-mo-do-den-decal-candy-mo-cao-cap",
    "shortDescription": "FREESHIP tem toàn quốc & thiết kế theo yêu cầu Có dịch vụ ship tem xe ra nước ngoài Đặt lịch & tư vấn decal tem xe liên hệ Zalo 0904560191. Khách hàng có thể tùy chỉnh thiết kế tem bằng cách thêm têm,\nsố hay logo... thậm chí đổi màu sắc và chất liệu theo ý thích của bạn. Vui lòng liên hệ để được tư vấn tốt nhất!\nBảo hành 12 tháng về tem khi dán trực tiếp tại cửa hàng.\n ",
    "longDescription": "FREESHIP tem toàn quốc & thiết kế theo yêu cầu Có dịch vụ ship tem xe ra nước ngoài Đặt lịch & tư vấn decal tem xe liên hệ Zalo 0904560191. Khách hàng có thể tùy chỉnh thiết kế tem bằng cách thêm têm,\nsố hay logo... thậm chí đổi màu sắc và chất liệu theo ý thích của bạn. Vui lòng liên hệ để được tư vấn tốt nhất!\nBảo hành 12 tháng về tem khi dán trực tiếp tại cửa hàng.\n\nVì sao lựa chọn tem xe của Q-Decal? \n> Chất liệu cao cấp nhập khẩu 100% loại 3 lớp cực bền\n> Co giãn 4 chiều thoải mái và giấy rất dày dặn\n> Tùy chọn chất liệu thường, nhôm hoặc nhôm xước \n> Tem được cán 1 lớp bảo vệ nhám hoặc mờ tùy theo yêu cầu ",
    "price": "580000",
    "categoryName": "",
    "categoryPath": ""
  },
  {
    "id": 2380904,
    "name": "Tem trùm Winner X Samurai Nhật Bản decal 3 lớp cao cấp",
    "code": "",
    "img": "http://upload2.webbnc.vn/uploadv2/web/97/9724/product/2022/07/24/08/55/1658646817_img_1655181580567_1655181928818.jpg",
    "subImg": [
      "http://upload2.webbnc.vn/uploadv2/web/97/9724/product/2022/07/24/08/54/1658646784_img_1655181580570_1655181932794.jpg",
      "http://upload2.webbnc.vn/uploadv2/web/97/9724/product/2022/07/24/08/55/1658646787_img_1655181580569_1655181931954.jpg",
      "http://upload2.webbnc.vn/uploadv2/web/97/9724/product/2022/07/24/08/55/1658646790_img_1655181580568_1655181930894.jpg",
      "http://upload2.webbnc.vn/uploadv2/web/97/9724/product/2022/07/24/08/55/1658646817_img_1655181580567_1655181928818.jpg"
    ],
    "seo": "tem-trum-winner-x-samurai-nhat-ban-decal-3-lop-cao-cap",
    "shortDescription": "FREESHIP tem toàn quốc & thiết kế theo yêu cầu Có dịch vụ ship tem xe ra nước ngoài Đặt lịch & tư vấn decal tem xe liên hệ Zalo 0904560191. Khách hàng có thể tùy chỉnh thiết kế tem bằng cách thêm têm,\nsố hay logo... thậm chí đổi màu sắc và chất liệu theo ý thích của bạn. Vui lòng liên hệ để được tư vấn tốt nhất!\nBảo hành 12 tháng về tem khi dán trực tiếp tại cửa hàng.\n ",
    "longDescription": "FREESHIP tem toàn quốc & thiết kế theo yêu cầu Có dịch vụ ship tem xe ra nước ngoài Đặt lịch & tư vấn decal tem xe liên hệ Zalo 0904560191. Khách hàng có thể tùy chỉnh thiết kế tem bằng cách thêm têm,\nsố hay logo... thậm chí đổi màu sắc và chất liệu theo ý thích của bạn. Vui lòng liên hệ để được tư vấn tốt nhất!\nBảo hành 12 tháng về tem khi dán trực tiếp tại cửa hàng.\n\nVì sao lựa chọn tem xe của Q-Decal? \n> Chất liệu cao cấp nhập khẩu 100% loại 3 lớp cực bền\n> Co giãn 4 chiều thoải mái và giấy rất dày dặn\n> Tùy chọn chất liệu thường, nhôm hoặc nhôm xước \n> Tem được cán 1 lớp bảo vệ nhám hoặc mờ tùy theo yêu cầu ",
    "price": "380000",
    "categoryName": "",
    "categoryPath": ""
  },
  {
    "id": 2380902,
    "name": "Tem trùm Winner X V3 Xanh Xám decal 3 lớp cao cấp",
    "code": "",
    "img": "http://upload2.webbnc.vn/uploadv2/web/97/9724/product/2022/07/24/08/47/1658646357_img_1655727712812_1655821673666.jpg",
    "subImg": [
      "http://upload2.webbnc.vn/uploadv2/web/97/9724/product/2022/07/24/08/47/1658646357_img_1655727712812_1655821673666.jpg",
      "http://upload2.webbnc.vn/uploadv2/web/97/9724/product/2022/07/24/08/47/1658646359_img_1655727712813_1655821679129.jpg"
    ],
    "seo": "tem-trum-winner-x-v3-xanh-xam-decal-3-lop-cao-ca",
    "shortDescription": "FREESHIP tem toàn quốc & thiết kế theo yêu cầu Có dịch vụ ship tem xe ra nước ngoài Đặt lịch & tư vấn decal tem xe liên hệ Zalo 0904560191. Khách hàng có thể tùy chỉnh thiết kế tem bằng cách thêm têm,\nsố hay logo... thậm chí đổi màu sắc và chất liệu theo ý thích của bạn. Vui lòng liên hệ để được tư vấn tốt nhất!\nBảo hành 12 tháng về tem khi dán trực tiếp tại cửa hàng.FREESHIP tem toàn quốc & thiết kế theo yêu cầu Có dịch vụ ship tem xe ra nước ngoài Đặt lịch & tư vấn decal tem xe liên hệ Zalo\n0904560191. Khách hàng có thể tùy chỉnh thiết kế tem bằng cách thêm têm, số hay logo... thậm chí đổi màu sắc và chất liệu theo ý thích của bạn. Vui lòng liên hệ để được tư vấn tốt nhất!\nBảo hành 12 tháng về tem khi dán trực tiếp tại cửa hàng.\n ",
    "longDescription": "FREESHIP tem toàn quốc & thiết kế theo yêu cầu Có dịch vụ ship tem xe ra nước ngoài Đặt lịch & tư vấn decal tem xe liên hệ Zalo 0904560191. Khách hàng có thể tùy chỉnh thiết kế tem bằng cách thêm têm,\nsố hay logo... thậm chí đổi màu sắc và chất liệu theo ý thích của bạn. Vui lòng liên hệ để được tư vấn tốt nhất!\nBảo hành 12 tháng về tem khi dán trực tiếp tại cửa hàng.FREESHIP tem toàn quốc & thiết kế theo yêu cầu Có dịch vụ ship tem xe ra nước ngoài Đặt lịch & tư vấn decal tem xe liên hệ Zalo\n0904560191. Khách hàng có thể tùy chỉnh thiết kế tem bằng cách thêm têm, số hay logo... thậm chí đổi màu sắc và chất liệu theo ý thích của bạn. Vui lòng liên hệ để được tư vấn tốt nhất!\nBảo hành 12 tháng về tem khi dán trực tiếp tại cửa hàng.\n\nVì sao lựa chọn tem xe của Q-Decal? \n> Chất liệu cao cấp nhập khẩu 100% loại 3 lớp cực bền\n> Co giãn 4 chiều thoải mái và giấy rất dày dặn\n> Tùy chọn chất liệu thường, nhôm hoặc nhôm xước \n> Tem được cán 1 lớp bảo vệ nhám hoặc mờ tùy theo yêu cầu \n#Temxe #R15v3 #Temtrum #SH #WinnerX #Decal #Qdecal #Qteam #CandyBong #CandyNham #Wace110 #Yamaha #CB150 #CB650F #Honda #MSX #WACE #Decal #Kawasaki #Z800 #Yamaha #R1M",
    "price": "380000",
    "categoryName": "",
    "categoryPath": ""
  }
]